pyqt5_concurrent-0.1.7.dist-info/METADATA
pyqt5_concurrent-0.1.7.dist-info/WHEEL
pyqt5_concurrent-0.1.7.dist-info/entry_points.txt
pyqt5_concurrent-0.1.7.dist-info/licenses/LICENSE
pyqt5_concurrent/Future.py
pyqt5_concurrent/Qt.py
pyqt5_concurrent/Task.py
pyqt5_concurrent/TaskExecutor.py
pyqt5_concurrent/__init__.py
pyqt5_concurrent-0.1.7.dist-info/RECORD
