Metadata-Version: 2.1
Name: pyqt5-concurrent
Version: 0.1.7
Summary: QThreadPool based task concurrency library in pyqt5
Author-Email: AresConnor <aresconnor867@gmail.com>
License: MIT
Requires-Python: <3.13,>=3.7
